odoo/addons/mrp_production_auto_post_inventory/README.rst
odoo/addons/mrp_production_auto_post_inventory/__init__.py
odoo/addons/mrp_production_auto_post_inventory/__manifest__.py
odoo/addons/mrp_production_auto_post_inventory/data/cron.xml
odoo/addons/mrp_production_auto_post_inventory/i18n/it.po
odoo/addons/mrp_production_auto_post_inventory/i18n/mrp_production_auto_post_inventory.pot
odoo/addons/mrp_production_auto_post_inventory/i18n/pt_BR.po
odoo/addons/mrp_production_auto_post_inventory/models/__init__.py
odoo/addons/mrp_production_auto_post_inventory/models/company.py
odoo/addons/mrp_production_auto_post_inventory/models/mrp_production.py
odoo/addons/mrp_production_auto_post_inventory/models/res_config_settings.py
odoo/addons/mrp_production_auto_post_inventory/readme/CONTRIBUTORS.rst
odoo/addons/mrp_production_auto_post_inventory/readme/DESCRIPTION.rst
odoo/addons/mrp_production_auto_post_inventory/readme/USAGE.rst
odoo/addons/mrp_production_auto_post_inventory/static/description/AutoPostInventory_Option.png
odoo/addons/mrp_production_auto_post_inventory/static/description/icon.png
odoo/addons/mrp_production_auto_post_inventory/static/description/index.html
odoo/addons/mrp_production_auto_post_inventory/tests/__init__.py
odoo/addons/mrp_production_auto_post_inventory/tests/test_mrp_production.py
odoo/addons/mrp_production_auto_post_inventory/views/res_config_settings.xml
odoo/addons/mrp_production_auto_post_inventory/wizard/__init__.py
odoo/addons/mrp_production_auto_post_inventory/wizard/mrp_product_produce.py
odoo12_addon_mrp_production_auto_post_inventory-12.0.1.1.1.dist-info/METADATA
odoo12_addon_mrp_production_auto_post_inventory-12.0.1.1.1.dist-info/WHEEL
odoo12_addon_mrp_production_auto_post_inventory-12.0.1.1.1.dist-info/top_level.txt
odoo12_addon_mrp_production_auto_post_inventory-12.0.1.1.1.dist-info/RECORD
